main.py
mcp_github_cli-0.2.0.dist-info/METADATA
mcp_github_cli-0.2.0.dist-info/WHEEL
mcp_github_cli-0.2.0.dist-info/entry_points.txt
mcp_github_cli-0.2.0.dist-info/top_level.txt
mcp_github_cli-0.2.0.dist-info/RECORD
