Metadata-Version: 2.4
Name: mcp-github-cli
Version: 0.2.0
Summary: GitHub CLI extension for MCP that provides focused GraphQL and REST API tools.
Author: Block
License: MIT
Project-URL: Homepage, https://github.com/michaelneale/mcp-github-cli/
Requires-Python: >=3.12
Requires-Dist: mcp[cli]>=1.3.0
